{
  "_class": "group",
  "do_objectID": "58D5321B-F516-4CCA-A23C-5422D33E1ADA",
  "exportOptions": {
    "_class": "exportOptions",
    "exportFormats": [
    ],
    "includedLayerIds": [
    ],
    "layerOptions": 0,
    "shouldTrim": false
  },
  "frame": {
    "_class": "rect",
    "constrainProportions": false,
    "height": 391,
    "width": 492,
    "x": 1194,
    "y": 162
  },
  "hasClickThrough": false,
  "isFlippedHorizontal": false,
  "isFlippedVertical": false,
  "isLocked": false,
  "isVisible": false,
  "layerListExpandedType": 0,
  "layers": [
    {
      "class": "shapeGroup",
      "id": "DC174039-4614-4501-A65D-3E6397262C78"
    },
    {
      "class": "shapeGroup",
      "id": "60A2F5DC-03F5-47CD-B884-1ABE773A10F7"
    },
    {
      "class": "shapeGroup",
      "id": "E30783E8-2DE0-46A9-9152-8BA2EAAB3A05"
    },
    {
      "class": "shapeGroup",
      "id": "5C64F7C9-3E87-43E0-941F-51DAE496DF97"
    },
    {
      "class": "shapeGroup",
      "id": "A9970F08-16CD-4C91-A6F5-0E6C6706A2A3"
    },
    {
      "class": "shapeGroup",
      "id": "5C800FF6-DB89-406B-A835-B9DA24C92200"
    },
    {
      "class": "shapeGroup",
      "id": "66A8DFAE-1F9F-4C04-AAE7-BEA369B6D22F"
    },
    {
      "class": "shapeGroup",
      "id": "2E8995F6-C92E-4357-B81A-84361DCD0107"
    }
  ],
  "name": "Group",
  "nameIsFixed": false,
  "resizingConstraint": 63,
  "resizingType": 0,
  "rotation": 0,
  "shouldBreakMaskChain": false,
  "style": {
    "_class": "style",
    "endDecorationType": 0,
    "miterLimit": 10,
    "startDecorationType": 0
  }
}