{
  "_class": "group",
  "do_objectID": "CE6763A7-1CC6-49FA-880D-3DDEEDA2D7DA",
  "exportOptions": {
    "_class": "exportOptions",
    "exportFormats": [
    ],
    "includedLayerIds": [
    ],
    "layerOptions": 0,
    "shouldTrim": false
  },
  "frame": {
    "_class": "rect",
    "constrainProportions": false,
    "height": 200,
    "width": 180,
    "x": 20,
    "y": 20
  },
  "hasClickThrough": false,
  "isFlippedHorizontal": false,
  "isFlippedVertical": false,
  "isLocked": false,
  "isVisible": true,
  "layerListExpandedType": 0,
  "layers": [
    {
      "class": "shapeGroup",
      "id": "9F930E7B-EB66-4570-9542-879BF3885F27"
    },
    {
      "class": "shapeGroup",
      "id": "3417A539-3EBA-4F02-9C7E-00B87073E700"
    },
    {
      "class": "text",
      "id": "CCA916E8-DC33-4CE9-806A-D64E94351F9A"
    },
    {
      "class": "text",
      "id": "68EBE8C5-FAA8-4A62-B3C2-5ABAA2147235"
    },
    {
      "class": "text",
      "id": "F88C2AB1-B7EA-4E0E-87F5-4B108401B2D0"
    }
  ],
  "name": "Swatch: #292E55",
  "nameIsFixed": false,
  "resizingConstraint": 63,
  "resizingType": 0,
  "rotation": 0,
  "shouldBreakMaskChain": false,
  "style": {
    "_class": "style",
    "endDecorationType": 0,
    "miterLimit": 10,
    "startDecorationType": 0
  }
}